colord/__init__.py
colord/colord.py
colord-0.0.6.dist-info/LICENSE
colord-0.0.6.dist-info/METADATA
colord-0.0.6.dist-info/WHEEL
colord-0.0.6.dist-info/top_level.txt
colord-0.0.6.dist-info/RECORD
