Metadata-Version: 2.1
Name: colord
Version: 0.0.6
Summary: colord is a python package for multiplatform colors.
Home-page: https://github.com/hinzee/colord
Author: hinzee
Author-email: hinzee@seznam.cz
License: MIT
Platform: UNKNOWN
Classifier: Development Status :: 4 - Beta
Classifier: License :: OSI Approved :: MIT License
Classifier: Programming Language :: Python
Classifier: Programming Language :: Python :: 3.5
Classifier: Programming Language :: Python :: 3.6
Classifier: Topic :: Software Development :: Libraries
Classifier: Topic :: Software Development :: Libraries :: Python Modules
Classifier: Intended Audience :: Developers
Requires-Python: >=3.5
Requires-Dist: colorama
